core_extract_and_load/__init__.py
core_extract_and_load/cleaning_and_saving_s3.py
core_extract_and_load/demo.py
core_extract_and_load/main.py
core_extract_and_load-1.0.0.dist-info/METADATA
core_extract_and_load-1.0.0.dist-info/WHEEL
core_extract_and_load-1.0.0.dist-info/top_level.txt
core_extract_and_load-1.0.0.dist-info/RECORD
